testomaton/__init__.py
testomaton/beaver.py
testomaton/constraint.py
testomaton/errors.py
testomaton/generator.py
testomaton/jigsaw.py
testomaton/model.py
testomaton/solver.py
testomaton/tomato.py
testomaton/validator.py
testomaton-0.4.2.dist-info/licenses/LICENSE
testomaton-0.4.2.dist-info/METADATA
testomaton-0.4.2.dist-info/WHEEL
testomaton-0.4.2.dist-info/entry_points.txt
testomaton-0.4.2.dist-info/top_level.txt
testomaton-0.4.2.dist-info/RECORD
