Metadata-Version: 2.4
Name: testomaton
Version: 0.4.2
Summary: Model based combinatorial test data generator
Home-page: https://bitbucket.org/testify-no/tomato
Author: Testify AS
Author-email: tomato@testify.no
License: GNU Affero General Public License v3 or later (AGPLv3+)
Project-URL: Changelog, https://bitbucket.org/testify-no/tomato/src/develop/CHANGELOG.md
Keywords: testing pairwise test_generation
Classifier: Development Status :: 4 - Beta
Classifier: Programming Language :: Python :: 3
Classifier: License :: OSI Approved :: GNU Affero General Public License v3 or later (AGPLv3+)
Classifier: Operating System :: OS Independent
Classifier: Environment :: Console
Classifier: Topic :: Software Development :: Libraries :: Python Modules
Classifier: Topic :: Software Development :: Testing
Classifier: Programming Language :: Python :: 3
Requires-Python: >=3.7
License-File: LICENSE
Requires-Dist: python-sat
Requires-Dist: pyparsing
Requires-Dist: pyaml
Requires-Dist: regex
Dynamic: author
Dynamic: author-email
Dynamic: classifier
Dynamic: description
Dynamic: description-content-type
Dynamic: home-page
Dynamic: keywords
Dynamic: license
Dynamic: license-file
Dynamic: project-url
Dynamic: requires-dist
Dynamic: requires-python
Dynamic: summary
